{
  "Mode 1": {
    "border-radius-xs": {
      "value": "var(--border-radius-2)",
      "type": "float",
      "originalName": "border/radius/xs"
    },
    "border-radius-sm": {
      "value": "var(--border-radius-4)",
      "type": "float",
      "originalName": "border/radius/sm"
    },
    "border-radius-md": {
      "value": "var(--border-radius-5)",
      "type": "float",
      "originalName": "border/radius/md"
    },
    "border-radius-lg": {
      "value": "var(--border-radius-8)",
      "type": "float",
      "originalName": "border/radius/lg"
    },
    "border-radius-xl": {
      "value": "var(--border-radius-16)",
      "type": "float",
      "originalName": "border/radius/xl"
    },
    "border-radius-full-round": {
      "value": "var(--border-radius-round)",
      "type": "float",
      "originalName": "border/radius/full-round"
    },
    "border-width-default": {
      "value": "var(--border-width-1)",
      "type": "float",
      "originalName": "border/width/default"
    },
    "border-width-selected": {
      "value": "var(--border-width-2)",
      "type": "float",
      "originalName": "border/width/selected"
    },
    "border-width-focused": {
      "value": "var(--border-width-2)",
      "type": "float",
      "originalName": "border/width/focused"
    }
  }
}